phantombuster/__init__.py
phantombuster/analysis.py
phantombuster/bamindexer.py
phantombuster/cli.py
phantombuster/config_files.py
phantombuster/core.py
phantombuster/error_corrector.py
phantombuster/exceptions.py
phantombuster/handler.py
phantombuster/io_.py
phantombuster/plumbing.py
phantombuster/porcelain.py
phantombuster/project.py
phantombuster/scheduler.py
phantombuster/statistics.py
phantombuster/store.py
phantombuster/stores.py
phantombuster/vault.py
phantombuster/visualisation.py
phantombuster/remoter/__init__.py
phantombuster/remoter/async_.py
phantombuster/remoter/cli.py
phantombuster/remoter/globaladdress.py
phantombuster/remoter/lock.py
phantombuster/remoter/logging_.py
phantombuster/remoter/messages.py
phantombuster/remoter/persisters.py
phantombuster/remoter/scheduler.py
phantombuster/remoter/serialization.py
phantombuster/remoter/server.py
phantombuster/remoter/socket_.py
phantombuster/remoter/store.py
phantombuster/remoter/task.py
phantombuster/remoter/worker.py
phantombuster-0.20.0.dist-info/METADATA
phantombuster-0.20.0.dist-info/WHEEL
phantombuster-0.20.0.dist-info/entry_points.txt
phantombuster-0.20.0.dist-info/top_level.txt
phantombuster-0.20.0.dist-info/RECORD
