Metadata-Version: 2.4
Name: phantombuster
Version: 0.20.0
Summary: Bioinformatical tool to remove sequencing artifacts originating from single-nucleotide errors and index hopping from barcode-based experiments
Author-email: Simon Haendeler <simon.emanuel.haendeler@univie.ac.at>
Requires-Python: <3.13,>=3.9
Requires-Dist: pysam<1.0.0,>=0.22.0
Requires-Dist: regex<2025.0.0,>=2024.11.6
Requires-Dist: click==8.1.8
Requires-Dist: trio<1.0.0,>=0.22.0
Requires-Dist: scipy<2.0.0,>=1.10.1
Requires-Dist: polars<2.0,>=1.0
Requires-Dist: pyzmq<27.0.0,>=26.3.0
Requires-Dist: bokeh>=3.4.3
